AUTHORS.rst
CONTRIBUTING.rst
HISTORY.rst
LICENSE
MANIFEST.in
README.rst
setup.cfg
setup.py
docs/Makefile
docs/authors.rst
docs/conf.py
docs/contributing.rst
docs/history.rst
docs/index.rst
docs/installation.rst
docs/make.bat
docs/readme.rst
docs/usage.rst
sample/liximomo.sftp-1.12.10.vsix
tests/__init__.py
tests/test_vscode_sftp_alias.py
vscode_sftp_alias/__init__.py
vscode_sftp_alias/vscode_sftp_alias.py
vscode_sftp_alias.egg-info/PKG-INFO
vscode_sftp_alias.egg-info/SOURCES.txt
vscode_sftp_alias.egg-info/dependency_links.txt
vscode_sftp_alias.egg-info/not-zip-safe
vscode_sftp_alias.egg-info/top_level.txt